nptk/__init__.py
nptk/__main__.py
nptk/config.py
nptk/example.py
nptk/exceptions.py
nptk/lims/__init__.py
nptk/lims/dataclasses.py
nptk/lims/local_paths.py
nptk/lims/queries.py
nptk/lims/utils.py
nptk/lims/wkft.py
nptk-0.1.4.dist-info/entry_points.txt
nptk-0.1.4.dist-info/LICENSE
nptk-0.1.4.dist-info/WHEEL
nptk-0.1.4.dist-info/METADATA
nptk-0.1.4.dist-info/RECORD
