Metadata-Version: 2.1
Name: nptk
Version: 0.1.4
Summary: Awesome `nptk` is a Python cli/package created with https://github.com/TezRomacH/python-package-template
Home-page: https://github.com/nptk/nptk
License: MIT
Author: nptk
Author-email: chrism@alleninstitute.org
Requires-Python: >=3.9,<4.0
Classifier: Development Status :: 3 - Alpha
Classifier: Intended Audience :: Developers
Classifier: License :: OSI Approved :: MIT License
Classifier: Operating System :: OS Independent
Classifier: Programming Language :: Python :: 3
Classifier: Programming Language :: Python :: 3.10
Classifier: Programming Language :: Python :: 3.9
Classifier: Topic :: Software Development :: Libraries :: Python Modules
Requires-Dist: psycopg2 (>=2.9.3,<3.0.0)
Requires-Dist: rich (>=10.14.0,<11.0.0)
Requires-Dist: typer[all] (>=0.4.0,<0.5.0)
Project-URL: Repository, https://github.com/nptk/nptk
